dagster_webserver/__init__.py
dagster_webserver/__main__.py
dagster_webserver/app.py
dagster_webserver/cli.py
dagster_webserver/debug.py
dagster_webserver/external_assets.py
dagster_webserver/graphql.py
dagster_webserver/py.typed
dagster_webserver/version.py
dagster_webserver/webserver.py
dagster_webserver/graphiql/graphiql-plugin-explorer-style.css
dagster_webserver/graphiql/graphiql-plugin-explorer.umd.js
dagster_webserver/graphiql/graphiql.min.css
dagster_webserver/graphiql/graphiql.min.js
dagster_webserver/graphiql/react-dom.production.min.js
dagster_webserver/graphiql/react.production.min.js
dagster_webserver/schema/__init__.py
dagster_webserver/templates/__init__.py
dagster_webserver/templates/graphiql.py
dagster_webserver/webapp/build/404.html
dagster_webserver/webapp/build/Dagster_world.mp4
dagster_webserver/webapp/build/csp-header.txt
dagster_webserver/webapp/build/favicon-run-failed.svg
dagster_webserver/webapp/build/favicon-run-pending.svg
dagster_webserver/webapp/build/favicon-run-success.svg
dagster_webserver/webapp/build/favicon.ico
dagster_webserver/webapp/build/favicon.png
dagster_webserver/webapp/build/favicon.svg
dagster_webserver/webapp/build/index.html
dagster_webserver/webapp/build/manifest.json
dagster_webserver/webapp/build/robots.txt
dagster_webserver/webapp/build/_next/static/9kWzxM-JC-5sWBjfqTtzo/_buildManifest.js
dagster_webserver/webapp/build/_next/static/9kWzxM-JC-5sWBjfqTtzo/_ssgManifest.js
dagster_webserver/webapp/build/_next/static/chunks/1854.e0f828b8337dda0e.js
dagster_webserver/webapp/build/_next/static/chunks/1854.e0f828b8337dda0e.js.map
dagster_webserver/webapp/build/_next/static/chunks/1885.16ab3dc299a1fa6a.js
dagster_webserver/webapp/build/_next/static/chunks/1885.16ab3dc299a1fa6a.js.map
dagster_webserver/webapp/build/_next/static/chunks/197.280dd33d6c3d790c.js
dagster_webserver/webapp/build/_next/static/chunks/197.280dd33d6c3d790c.js.map
dagster_webserver/webapp/build/_next/static/chunks/2024.46ee83a1fa7362cb.js
dagster_webserver-1.12.13.dist-info/licenses/LICENSE
dagster_webserver-1.12.13.dist-info/METADATA
dagster_webserver-1.12.13.dist-info/WHEEL
dagster_webserver-1.12.13.dist-info/entry_points.txt
dagster_webserver-1.12.13.dist-info/top_level.txt
dagster_webserver-1.12.13.dist-info/RECORD
